anonymizeip/__init__.py
anonymizeip/__version__.py
anonymizeip/anonymize_ip.py
anonymizeip-1.0.0.dist-info/METADATA
anonymizeip-1.0.0.dist-info/RECORD
anonymizeip-1.0.0.dist-info/WHEEL
anonymizeip-1.0.0.dist-info/top_level.txt
