Metadata-Version: 2.1
Name: anonymizeip
Version: 1.0.0
Summary: Python library for anonymizing IP addresses
Home-page: https://github.com/samuelmeuli/anonymize-ip
Author: Samuel Meuli
Author-email: dev@samuelmeuli.com
License: MIT
Platform: UNKNOWN
Classifier: License :: OSI Approved :: MIT License
Classifier: Programming Language :: Python
Classifier: Programming Language :: Python :: 3
Classifier: Programming Language :: Python :: Implementation :: CPython
Classifier: Programming Language :: Python :: Implementation :: PyPy
Requires-Python: >=3.3.0
